[
  {
    "エリート ゼイディー ランクカップ(デュオ バトルロイヤル)": {
      "displayDataId": "s35_zadieranked_duos",
      "metadata": {
        "minimumAccountLevel": 50,
        "AccountLockType": "Window",
        "DisqualifyType": "Window",
        "tournamentType": "RankedCup"
      },
      "loading_screen_image": "https://cdn2.unrealengine.com/en-fnce-35-00-dashberry-elitezadie-rankedcups-br-discoverytile-1920x1080-1920x1080-39785b12b3d9.jpg",
      "playlist_tile_image": "https://cdn2.unrealengine.com/jp-fnce-35-00-dashberry-elitezadie-rankedcups-br-discoverytile-1920x1080-1920x1080-7896568a903d.jpg",
      "poster_front_image": "https://cdn2.unrealengine.com/fnce-35-00-competitive-zadierankedcup-poster-front-750x1080-9bdc64fd8901.jpg",
      "tournament_view_background_image": "https://cdn2.unrealengine.com/fnce-35-00-rankedcup-elitezadie-in-game-compete-tab-grouptexture-1560x1024-1560x1024-78269c07758c.jpg",
      "S35_RankedCupEliteDuos_Event1_ASIA": [
        {
          "beginTime": "2025-05-16T09:00:00Z",
          "endTime": "2025-05-16T13:00:00Z",
          "beginTime_UNIX": 1747386000,
          "beginTime_JST": "2025-05-16 18:00:00",
          "endTime_UNIX": 1747400400,
          "endTime_JST": "2025-05-16 22:00:00",
          "playlistId": "Playlist_ShowdownTournament_RC_Duos",
          "matchCap": 0,
          "additionalRequirements": [
            "currentRanking:ranked-br:15",
            "mfa",
            "adps:g-a81a33a3b9a7",
            "eula:s35_ranked_rules"
          ],
          "requireAllTokens": [],
          "requireAnyTokens": [],
          "requireNoneTokensCaller": [
            "EpicAccountPrizingRestriction_v2",
            "Permanent_Tournament_Ban"
          ],
          "requireAllTokensCaller": [],
          "requireAnyTokensCaller": [],
          "payouts": [
            {
              "threshold": 50,
              "rewardType": "game",
              "quantity": 1,
              "value": "AthenaGlider:umbrella_rankedhalt"
            },
            {
              "threshold": 10,
              "rewardType": "game",
              "quantity": 1,
              "value": "AthenaCharacter:character_rankedtroopernoble"
            }
          ]
        }
      ],
      "S35_RankedCupEliteDuos_Event2_ASIA": [
        {
          "beginTime": "2025-05-23T09:00:00Z",
          "endTime": "2025-05-23T13:00:00Z",
          "beginTime_UNIX": 1747990800,
          "beginTime_JST": "2025-05-23 18:00:00",
          "endTime_UNIX": 1748005200,
          "endTime_JST": "2025-05-23 22:00:00",
          "playlistId": "Playlist_ShowdownTournament_RC_Duos",
          "matchCap": 0,
          "additionalRequirements": [
            "currentRanking:ranked-br:15",
            "mfa",
            "adps:g-a81a33a3b9a7",
            "eula:s35_ranked_rules"
          ],
          "requireAllTokens": [],
          "requireAnyTokens": [],
          "requireNoneTokensCaller": [
            "EpicAccountPrizingRestriction_v2",
            "Permanent_Tournament_Ban"
          ],
          "requireAllTokensCaller": [],
          "requireAnyTokensCaller": [],
          "payouts": [
            {
              "threshold": 50,
              "rewardType": "game",
              "quantity": 1,
              "value": "AthenaGlider:umbrella_rankedhalt"
            },
            {
              "threshold": 10,
              "rewardType": "game",
              "quantity": 1,
              "value": "AthenaCharacter:character_rankedtroopernoble"
            }
          ]
        }
      ],
      "S35_RankedCupEliteDuos_Event3_ASIA": [
        {
          "beginTime": "2025-05-30T09:00:00Z",
          "endTime": "2025-05-30T13:00:00Z",
          "beginTime_UNIX": 1748595600,
          "beginTime_JST": "2025-05-30 18:00:00",
          "endTime_UNIX": 1748610000,
          "endTime_JST": "2025-05-30 22:00:00",
          "playlistId": "Playlist_ShowdownTournament_RC_Duos",
          "matchCap": 0,
          "additionalRequirements": [
            "currentRanking:ranked-br:15",
            "mfa",
            "adps:g-a81a33a3b9a7",
            "eula:s35_ranked_rules"
          ],
          "requireAllTokens": [],
          "requireAnyTokens": [],
          "requireNoneTokensCaller": [
            "EpicAccountPrizingRestriction_v2",
            "Permanent_Tournament_Ban"
          ],
          "requireAllTokensCaller": [],
          "requireAnyTokensCaller": [],
          "payouts": [
            {
              "threshold": 50,
              "rewardType": "game",
              "quantity": 1,
              "value": "AthenaGlider:umbrella_rankedhalt"
            },
            {
              "threshold": 10,
              "rewardType": "game",
              "quantity": 1,
              "value": "AthenaCharacter:character_rankedtroopernoble"
            }
          ]
        }
      ]
    }
  }
]