[
  {
    "FNCS ディビジョン2 プラクティス": {
      "eventId": "epicgames_S37_FNCSDivisionalCup_Division2_ASIA",
      "displayDataId": "s37_division2",
      "square_poster_image": "https://cdn2.unrealengine.com/fnce-37-00-globalchampionship-single-800x800-800x800-5110ebfedc33.jpg",
      "tournament_view_background_image": "https://cdn2.unrealengine.com/fnce-37-00-globalchampionship-group-1560x1024-1560x1024-760b1c424c17.jpg",
      "loading_screen_image": "https://cdn2.unrealengine.com/en-fnce-33-30-competitive-discoverytile-division2cup-1920x1080-1920x1080-af9665dddce6.jpg",
      "playlist_title_image": "https://cdn2.unrealengine.com/en-en-fnce-37-00-globalchampionship-discoverytile-division2cup-1920x1080-1920x1080-7ef7800e53cb.jpg",
      "metadata": {
        "requireSystemFeatures": [
          "SecureBoot",
          "CryptoProcessor"
        ],
        "tournamentType": "FNCS",
        "TeamLockType": "Week",
        "webId": "S37_FNCSDivisionalCup_Division2",
        "minimumAccountLevel": 350,
        "DisqualifyType": "Event",
        "AccountLockType": "Window"
      },
      "S37_FNCSDivisionalCup_Division2_Week1Day1_ASIA": {
        "beginTime": "2025-08-13T09:00:01Z",
        "beginTime_UNIX": 1755075601,
        "beginTime_JST": "2025-08-13 18:00:01",
        "endTime": "2025-08-13T12:00:01Z",
        "endTime_UNIX": 1755086401,
        "endTime_JST": "2025-08-13 21:00:01",
        "playlistId": "Playlist_ShowdownTournament_NPM_Trios",
        "matchCap": 10,
        "additionalRequirements": [
          "eula:s37_divpractice_rules",
          "adps:g-a81a33a3b9a7",
          "mfa"
        ],
        "requireAllTokens": [
          "S37_CashCup_Qualified"
        ],
        "requireAllTokensCaller": [],
        "requireAnyTokens": [
          "S34_FNCS_Division1_ASIA",
          "S33_FNCS_Division1_ASIA",
          "S34_FNCS_Division2_ASIA",
          "S33_FNCS_Division2_ASIA"
        ],
        "requireAnyTokensCaller": [],
        "requireNoneTokensCaller": [
          "EpicAccountPrizingRestriction_v2",
          "S37_DivisionLock_Division1Week1_ASIA",
          "S37_FNCS_Banned",
          "S37_DivisionLock_Division3Week1_ASIA",
          "Permanent_Tournament_Ban"
        ],
        "payouts": [
          {
            "scoringType": "value",
            "threshold": 0,
            "rewardType": "token",
            "quantity": 1,
            "value": "S37_DivisionLock_Division2Week1_ASIA"
          },
          {
            "scoringType": "value",
            "threshold": 0,
            "rewardType": "token",
            "quantity": 1,
            "value": "S34_FNCS_Division2_ASIA"
          }
        ]
      },
      "S37_FNCSDivisionalCup_Division2_Week1Day2_ASIA": {
        "beginTime": "2025-08-14T09:00:01Z",
        "beginTime_UNIX": 1755162001,
        "beginTime_JST": "2025-08-14 18:00:01",
        "endTime": "2025-08-14T12:00:01Z",
        "endTime_UNIX": 1755172801,
        "endTime_JST": "2025-08-14 21:00:01",
        "playlistId": "Playlist_ShowdownTournament_NPM_Trios",
        "matchCap": 10,
        "additionalRequirements": [
          "eula:s37_divpractice_rules",
          "adps:g-a81a33a3b9a7",
          "mfa"
        ],
        "requireAllTokens": [
          "S37_CashCup_Qualified"
        ],
        "requireAllTokensCaller": [],
        "requireAnyTokens": [
          "S34_FNCS_Division1_ASIA",
          "S33_FNCS_Division1_ASIA",
          "S34_FNCS_Division2_ASIA",
          "S33_FNCS_Division2_ASIA"
        ],
        "requireAnyTokensCaller": [],
        "requireNoneTokensCaller": [
          "EpicAccountPrizingRestriction_v2",
          "S37_DivisionLock_Division1Week1_ASIA",
          "S37_FNCS_Banned",
          "S37_DivisionLock_Division3Week1_ASIA",
          "Permanent_Tournament_Ban"
        ],
        "payouts": [
          {
            "scoringType": "value",
            "threshold": 0,
            "rewardType": "token",
            "quantity": 1,
            "value": "S37_DivisionLock_Division2Week1_ASIA"
          },
          {
            "scoringType": "value",
            "threshold": 0,
            "rewardType": "token",
            "quantity": 1,
            "value": "S34_FNCS_Division2_ASIA"
          },
          {
            "scoringType": "rank",
            "threshold": 20,
            "rewardType": "token",
            "quantity": 1,
            "value": "S34_FNCS_Division1_ASIA"
          }
        ]
      },
      "S37_FNCSDivisionalCup_Division2_Week2Day1_ASIA": {
        "beginTime": "2025-08-20T09:00:01Z",
        "beginTime_UNIX": 1755680401,
        "beginTime_JST": "2025-08-20 18:00:01",
        "endTime": "2025-08-20T12:00:01Z",
        "endTime_UNIX": 1755691201,
        "endTime_JST": "2025-08-20 21:00:01",
        "playlistId": "Playlist_ShowdownTournament_NPM_Trios",
        "matchCap": 10,
        "additionalRequirements": [
          "eula:s37_divpractice_rules",
          "adps:g-a81a33a3b9a7",
          "mfa"
        ],
        "requireAllTokens": [
          "S37_CashCup_Qualified"
        ],
        "requireAllTokensCaller": [],
        "requireAnyTokens": [
          "S34_FNCS_Division1_ASIA",
          "S33_FNCS_Division1_ASIA",
          "S34_FNCS_Division2_ASIA",
          "S33_FNCS_Division2_ASIA"
        ],
        "requireAnyTokensCaller": [],
        "requireNoneTokensCaller": [
          "S37_DivisionLock_Division3Week2_ASIA",
          "S37_FNCS_Banned",
          "Permanent_Tournament_Ban",
          "S37_DivisionLock_Division1Week2_ASIA",
          "EpicAccountPrizingRestriction_v2"
        ],
        "payouts": [
          {
            "scoringType": "value",
            "threshold": 0,
            "rewardType": "token",
            "quantity": 1,
            "value": "S37_DivisionLock_Division2Week2_ASIA"
          },
          {
            "scoringType": "value",
            "threshold": 0,
            "rewardType": "token",
            "quantity": 1,
            "value": "S34_FNCS_Division2_ASIA"
          }
        ]
      },
      "S37_FNCSDivisionalCup_Division2_Week2Day2_ASIA": {
        "beginTime": "2025-08-21T09:00:01Z",
        "beginTime_UNIX": 1755766801,
        "beginTime_JST": "2025-08-21 18:00:01",
        "endTime": "2025-08-21T12:00:01Z",
        "endTime_UNIX": 1755777601,
        "endTime_JST": "2025-08-21 21:00:01",
        "playlistId": "Playlist_ShowdownTournament_NPM_Trios",
        "matchCap": 10,
        "additionalRequirements": [
          "eula:s37_divpractice_rules",
          "adps:g-a81a33a3b9a7",
          "mfa"
        ],
        "requireAllTokens": [
          "S37_CashCup_Qualified"
        ],
        "requireAllTokensCaller": [],
        "requireAnyTokens": [
          "S34_FNCS_Division1_ASIA",
          "S33_FNCS_Division1_ASIA",
          "S34_FNCS_Division2_ASIA",
          "S33_FNCS_Division2_ASIA"
        ],
        "requireAnyTokensCaller": [],
        "requireNoneTokensCaller": [
          "S37_DivisionLock_Division3Week2_ASIA",
          "S37_FNCS_Banned",
          "Permanent_Tournament_Ban",
          "S37_DivisionLock_Division1Week2_ASIA",
          "EpicAccountPrizingRestriction_v2"
        ],
        "payouts": [
          {
            "scoringType": "value",
            "threshold": 0,
            "rewardType": "token",
            "quantity": 1,
            "value": "S37_DivisionLock_Division2Week2_ASIA"
          },
          {
            "scoringType": "value",
            "threshold": 0,
            "rewardType": "token",
            "quantity": 1,
            "value": "S34_FNCS_Division2_ASIA"
          },
          {
            "scoringType": "rank",
            "threshold": 20,
            "rewardType": "token",
            "quantity": 1,
            "value": "S34_FNCS_Division1_ASIA"
          }
        ]
      },
      "S37_FNCSDivisionalCup_Division2_Week3Day1_ASIA": {
        "beginTime": "2025-08-27T09:00:01Z",
        "beginTime_UNIX": 1756285201,
        "beginTime_JST": "2025-08-27 18:00:01",
        "endTime": "2025-08-27T12:00:01Z",
        "endTime_UNIX": 1756296001,
        "endTime_JST": "2025-08-27 21:00:01",
        "playlistId": "Playlist_ShowdownTournament_NPM_Trios",
        "matchCap": 10,
        "additionalRequirements": [
          "eula:s37_divpractice_rules",
          "adps:g-a81a33a3b9a7",
          "mfa"
        ],
        "requireAllTokens": [
          "S37_CashCup_Qualified"
        ],
        "requireAllTokensCaller": [],
        "requireAnyTokens": [
          "S34_FNCS_Division1_ASIA",
          "S33_FNCS_Division1_ASIA",
          "S34_FNCS_Division2_ASIA",
          "S33_FNCS_Division2_ASIA"
        ],
        "requireAnyTokensCaller": [],
        "requireNoneTokensCaller": [
          "EpicAccountPrizingRestriction_v2",
          "S37_DivisionLock_Division3Week3_ASIA",
          "S37_DivisionLock_Division1Week3_ASIA",
          "S37_FNCS_Banned",
          "Permanent_Tournament_Ban"
        ],
        "payouts": [
          {
            "scoringType": "value",
            "threshold": 0,
            "rewardType": "token",
            "quantity": 1,
            "value": "S37_DivisionLock_Division2Week3_ASIA"
          },
          {
            "scoringType": "value",
            "threshold": 0,
            "rewardType": "token",
            "quantity": 1,
            "value": "S34_FNCS_Division2_ASIA"
          }
        ]
      },
      "S37_FNCSDivisionalCup_Division2_Week3Day2_ASIA": {
        "beginTime": "2025-08-28T09:00:01Z",
        "beginTime_UNIX": 1756371601,
        "beginTime_JST": "2025-08-28 18:00:01",
        "endTime": "2025-08-28T12:00:01Z",
        "endTime_UNIX": 1756382401,
        "endTime_JST": "2025-08-28 21:00:01",
        "playlistId": "Playlist_ShowdownTournament_NPM_Trios",
        "matchCap": 10,
        "additionalRequirements": [
          "eula:s37_divpractice_rules",
          "adps:g-a81a33a3b9a7",
          "mfa"
        ],
        "requireAllTokens": [
          "S37_CashCup_Qualified"
        ],
        "requireAllTokensCaller": [],
        "requireAnyTokens": [
          "S34_FNCS_Division1_ASIA",
          "S33_FNCS_Division1_ASIA",
          "S34_FNCS_Division2_ASIA",
          "S33_FNCS_Division2_ASIA"
        ],
        "requireAnyTokensCaller": [],
        "requireNoneTokensCaller": [
          "EpicAccountPrizingRestriction_v2",
          "S37_DivisionLock_Division3Week3_ASIA",
          "S37_DivisionLock_Division1Week3_ASIA",
          "S37_FNCS_Banned",
          "Permanent_Tournament_Ban"
        ],
        "payouts": [
          {
            "scoringType": "value",
            "threshold": 0,
            "rewardType": "token",
            "quantity": 1,
            "value": "S37_DivisionLock_Division2Week3_ASIA"
          },
          {
            "scoringType": "value",
            "threshold": 0,
            "rewardType": "token",
            "quantity": 1,
            "value": "S34_FNCS_Division2_ASIA"
          },
          {
            "scoringType": "rank",
            "threshold": 20,
            "rewardType": "token",
            "quantity": 1,
            "value": "S34_FNCS_Division1_ASIA"
          }
        ]
      }
    }
  }
]