{
  "EventName": "Kai Cenat アイコンカップ",
  "eventId": "epicgames_S37_KaiCenatIconCup_ASIA",
  "displayDataId": "s37_kaicenat",
  "square_poster_image": "https://cdn2.unrealengine.com/800x800-800x800-306dd7be56dd.jpg",
  "tournament_view_background_image": "https://cdn2.unrealengine.com/1560x1024-1560x1024-93bb2442e9a3.jpg",
  "loading_screen_image": "未設定",
  "playlist_title_image": "https://cdn2.unrealengine.com/fnecojp-37-20-essayview-competitivecup-discoverplaylisttile-1920x1080-1920x1080-87465a58f478.jpg",
  "metadata": {
    "webId": "S37_KaiCenatIconCup",
    "minimumAccountLevel": 15,
    "DisqualifyType": "Window",
    "AccountLockType": "Window"
  },
  "platforms": [
    "IOS",
    "Android"
  ],
  "S37_KaiCenatIconCup_ASIA": {
    "beginTime_UNIX": 1757660400,
    "beginTime_JST": "2025-09-12 16:00:00",
    "endTime_UNIX": 1757665800,
    "endTime_JST": "2025-09-12 17:30:00",
    "playlistId": "Playlist_ShowdownTournament_ForbiddenFruitNoBuildSolo",
    "matchCap": 15,
    "additionalRequirements": [
      "eula:s37_kaicenat_rules",
      "adps:g-a81a33a3b9a7",
      "mfa"
    ],
    "requireAllTokens": [],
    "requireAllTokensCaller": [],
    "requireAnyTokens": [],
    "requireAnyTokensCaller": [],
    "requireNoneTokensCaller": [
      "EpicAccountPrizingRestriction_v2",
      "Permanent_Tournament_Ban"
    ],
    "ScoringRules": {
      "S37_KaiCenatIconCup_LeaderboardDef": {
        "scoringRuleSetId": "S37_KaiCenatIconCup_ScoringRules",
        "WindowLocation": "S37_KaiCenatIconCup_ASIA",
        "isMainWindowLeaderboard": true,
        "useIndividualScores": false,
        "onlyScoreTopN": -1,
        "payouts": [
          {
            "scoreId": "",
            "scoringType": "value",
            "threshold": 5,
            "rewardType": "game",
            "quantity": 1,
            "value": "AthenaDance:spray_essayview"
          },
          {
            "scoreId": "",
            "scoringType": "rank",
            "threshold": 300,
            "rewardType": "game",
            "quantity": 1,
            "value": "AthenaCharacter:character_essayviewpier"
          },
          {
            "scoreId": "",
            "scoringType": "rank",
            "threshold": 100,
            "rewardType": "game",
            "quantity": 1,
            "value": "AthenaCharacter:character_essayviewmyth"
          },
          {
            "scoreId": "",
            "scoringType": "rank",
            "threshold": 100,
            "rewardType": "game",
            "quantity": 1,
            "value": "AthenaDance:eid_essayviewmyth"
          },
          {
            "scoreId": "",
            "scoringType": "rank",
            "threshold": 100,
            "rewardType": "game",
            "quantity": 1,
            "value": "AthenaDance:eid_essayviewpier"
          },
          {
            "scoreId": "",
            "scoringType": "rank",
            "threshold": 100,
            "rewardType": "game",
            "quantity": 1,
            "value": "AthenaBackpack:backpack_essayviewmyth"
          },
          {
            "scoreId": "",
            "scoringType": "rank",
            "threshold": 100,
            "rewardType": "game",
            "quantity": 1,
            "value": "AthenaBackpack:backpack_essayviewpier"
          },
          {
            "scoreId": "",
            "scoringType": "rank",
            "threshold": 100,
            "rewardType": "game",
            "quantity": 1,
            "value": "AthenaPickaxe:pickaxe_essayviewmyth"
          },
          {
            "scoreId": "",
            "scoringType": "rank",
            "threshold": 100,
            "rewardType": "game",
            "quantity": 1,
            "value": "AthenaPickaxe:pickaxe_essayviewpier"
          },
          {
            "scoreId": "",
            "scoringType": "rank",
            "threshold": 100,
            "rewardType": "game",
            "quantity": 1,
            "value": "AthenaItemWrap:wrap_essayview"
          },
          {
            "scoreId": "",
            "scoringType": "rank",
            "threshold": 100,
            "rewardType": "game",
            "quantity": 1,
            "value": "CosmeticShoes:shoes_balletchockostrich"
          }
        ]
      }
    }
  }
}