{
  "EventName": "デュオ ランクカップ(リロード)",
  "eventId": "epicgames_S38_RankedCupReloadDuos_ASIA",
  "displayDataId": "s38_ranked_duosreload",
  "square_poster_image": "https://cdn2.unrealengine.com/fnce-33-30-tileview-ranked-cups-01-800x800-800x800-4181af1ba9f1.jpg",
  "tournament_view_background_image": "https://cdn2.unrealengine.com/fnce-33-30-textures-ranked-3up-1560x1024-1560x1018-e1321a692d66.jpg",
  "loading_screen_image": "https://cdn2.unrealengine.com/en-fneco-33-00-competitive-discoverytile-rankedcups-1080x1920-1920x1080-715a21161bce.jpg",
  "playlist_title_image": "https://cdn2.unrealengine.com/jp-fneco-33-00-competitive-discoverytile-rankedcups-1920x1080-1920x1080-39e21346cbba.jpg",
  "metadata": {
    "tournamentType": "RankedCup",
    "webId": "S38_RankedCupReloadDuos",
    "minimumAccountLevel": 50,
    "TrackedStats": [],
    "DisqualifyType": "Window",
    "AccountLockType": "Window"
  },
  "platforms": [
    "XboxOneGDK",
    "PS4",
    "XCloud",
    "Helios",
    "Luna",
    "IOS",
    "XB1",
    "XboxOne",
    "XSX",
    "Android",
    "LunaMobile",
    "Switch2",
    "PS5",
    "XCloudMobile",
    "Mac",
    "HeliosMobile",
    "GFN",
    "Switch",
    "GFNMobile",
    "Windows"
  ],
  "S38_RankedCupReloadDuos_Event1_ASIA": {
    "beginTime_UNIX": 1763024400,
    "beginTime_JST": "2025-11-13 18:00:00",
    "endTime_UNIX": 1763035200,
    "endTime_JST": "2025-11-13 21:00:00",
    "playlistId": "Playlist_ShowdownTournament_RC_DashBerryDuo_NoFill",
    "matchCap": 10,
    "additionalRequirements": [
      "eula:S38_ranked_rules",
      "adps:g-a81a33a3b9a7",
      "mfa",
      "currentRanking:ranked_blastberry_build:0"
    ],
    "requireAllTokens": [],
    "requireAllTokensCaller": [],
    "requireAnyTokens": [],
    "requireAnyTokensCaller": [],
    "requireNoneTokensCaller": [
      "EpicAccountPrizingRestriction_v2",
      "Permanent_Tournament_Ban"
    ],
    "ScoringRules": {
      "Lead_Default": {
        "scoringRuleSetId": "EmptyScoringRules",
        "WindowLocation": "S38_RankedCupReloadDuos_Event1_ASIA",
        "isMainWindowLeaderboard": true,
        "useIndividualScores": false,
        "onlyScoreTopN": -1,
        "payouts": [
          {
            "scoreId": "",
            "scoringType": "value",
            "threshold": 50,
            "rewardType": "game",
            "quantity": 1,
            "value": "AthenaGlider:umbrella_rankedstill"
          }
        ]
      },
      "RankedCupDuosReload_Bronze_LeaderboardDef": {
        "scoringRuleSetId": "ScoringRules_RankedCupDuosReload_Bronze",
        "WindowLocation": "S38_RankedCupReloadDuos_Event1_ASIA_Bronze",
        "isMainWindowLeaderboard": false,
        "useIndividualScores": false,
        "onlyScoreTopN": -1,
        "payouts": [
          {
            "scoreId": "",
            "scoringType": "value",
            "threshold": 50,
            "rewardType": "game",
            "quantity": 1,
            "value": "AthenaGlider:umbrella_rankedstill"
          }
        ]
      },
      "RankedCupDuosReload_Silver_LeaderboardDef": {
        "scoringRuleSetId": "ScoringRules_RankedCupDuosReload_Silver",
        "WindowLocation": "S38_RankedCupReloadDuos_Event1_ASIA_Silver",
        "isMainWindowLeaderboard": false,
        "useIndividualScores": false,
        "onlyScoreTopN": -1,
        "payouts": [
          {
            "scoreId": "",
            "scoringType": "value",
            "threshold": 50,
            "rewardType": "game",
            "quantity": 1,
            "value": "AthenaGlider:umbrella_rankedstill"
          }
        ]
      },
      "RankedCupDuosReload_Gold_LeaderboardDef": {
        "scoringRuleSetId": "ScoringRules_RankedCupDuosReload_Gold",
        "WindowLocation": "S38_RankedCupReloadDuos_Event1_ASIA_gold",
        "isMainWindowLeaderboard": false,
        "useIndividualScores": false,
        "onlyScoreTopN": -1,
        "payouts": [
          {
            "scoreId": "",
            "scoringType": "value",
            "threshold": 50,
            "rewardType": "game",
            "quantity": 1,
            "value": "AthenaGlider:umbrella_rankedstill"
          }
        ]
      },
      "RankedCupDuosReload_Platinum_LeaderboardDef": {
        "scoringRuleSetId": "ScoringRules_RankedCupDuosReload_Platinum",
        "WindowLocation": "S38_RankedCupReloadDuos_Event1_ASIA_platinum",
        "isMainWindowLeaderboard": false,
        "useIndividualScores": false,
        "onlyScoreTopN": -1,
        "payouts": [
          {
            "scoreId": "",
            "scoringType": "value",
            "threshold": 50,
            "rewardType": "game",
            "quantity": 1,
            "value": "AthenaGlider:umbrella_rankedstill"
          }
        ]
      },
      "RankedCupDuosReload_Diamond_LeaderboardDef": {
        "scoringRuleSetId": "ScoringRules_RankedCupDuosReload_Diamond",
        "WindowLocation": "S38_RankedCupReloadDuos_Event1_ASIA_diamond",
        "isMainWindowLeaderboard": false,
        "useIndividualScores": false,
        "onlyScoreTopN": -1,
        "payouts": [
          {
            "scoreId": "",
            "scoringType": "value",
            "threshold": 50,
            "rewardType": "game",
            "quantity": 1,
            "value": "AthenaGlider:umbrella_rankedstill"
          }
        ]
      },
      "RankedCupDuosReload_Elite_LeaderboardDef": {
        "scoringRuleSetId": "ScoringRules_RankedCupDuosReload_Elite",
        "WindowLocation": "S38_RankedCupReloadDuos_Event1_ASIA_elite",
        "isMainWindowLeaderboard": false,
        "useIndividualScores": false,
        "onlyScoreTopN": -1,
        "payouts": [
          {
            "scoreId": "",
            "scoringType": "value",
            "threshold": 50,
            "rewardType": "game",
            "quantity": 1,
            "value": "AthenaGlider:umbrella_rankedstill"
          }
        ]
      },
      "RankedCupDuosReload_Champion_LeaderboardDef": {
        "scoringRuleSetId": "ScoringRules_RankedCupDuosReload_Champion",
        "WindowLocation": "S38_RankedCupReloadDuos_Event1_ASIA_champion",
        "isMainWindowLeaderboard": false,
        "useIndividualScores": false,
        "onlyScoreTopN": -1,
        "payouts": [
          {
            "scoreId": "",
            "scoringType": "value",
            "threshold": 50,
            "rewardType": "game",
            "quantity": 1,
            "value": "AthenaGlider:umbrella_rankedstill"
          }
        ]
      },
      "RankedCupDuosReload_Unreal_LeaderboardDef": {
        "scoringRuleSetId": "ScoringRules_RankedCupDuosReload_Unreal",
        "WindowLocation": "S38_RankedCupReloadDuos_Event1_ASIA_unreal",
        "isMainWindowLeaderboard": false,
        "useIndividualScores": false,
        "onlyScoreTopN": -1,
        "payouts": [
          {
            "scoreId": "",
            "scoringType": "value",
            "threshold": 50,
            "rewardType": "game",
            "quantity": 1,
            "value": "AthenaGlider:umbrella_rankedstill"
          }
        ]
      }
    }
  },
  "S38_RankedCupReloadDuos_Event2_ASIA": {
    "beginTime_UNIX": 1763629200,
    "beginTime_JST": "2025-11-20 18:00:00",
    "endTime_UNIX": 1763640000,
    "endTime_JST": "2025-11-20 21:00:00",
    "playlistId": "Playlist_ShowdownTournament_RC_DashBerryDuo_NoFill",
    "matchCap": 10,
    "additionalRequirements": [
      "eula:S38_ranked_rules",
      "adps:g-a81a33a3b9a7",
      "mfa",
      "currentRanking:ranked_blastberry_build:0"
    ],
    "requireAllTokens": [],
    "requireAllTokensCaller": [],
    "requireAnyTokens": [],
    "requireAnyTokensCaller": [],
    "requireNoneTokensCaller": [
      "EpicAccountPrizingRestriction_v2",
      "Permanent_Tournament_Ban"
    ],
    "ScoringRules": {
      "Lead_Default": {
        "scoringRuleSetId": "EmptyScoringRules",
        "WindowLocation": "S38_RankedCupReloadDuos_Event2_ASIA",
        "isMainWindowLeaderboard": true,
        "useIndividualScores": false,
        "onlyScoreTopN": -1,
        "payouts": [
          {
            "scoreId": "",
            "scoringType": "value",
            "threshold": 50,
            "rewardType": "game",
            "quantity": 1,
            "value": "AthenaGlider:umbrella_rankedstill"
          }
        ]
      },
      "RankedCupDuosReload_Bronze_LeaderboardDef": {
        "scoringRuleSetId": "ScoringRules_RankedCupDuosReload_Bronze",
        "WindowLocation": "S38_RankedCupReloadDuos_Event2_ASIA_Bronze",
        "isMainWindowLeaderboard": false,
        "useIndividualScores": false,
        "onlyScoreTopN": -1,
        "payouts": [
          {
            "scoreId": "",
            "scoringType": "value",
            "threshold": 50,
            "rewardType": "game",
            "quantity": 1,
            "value": "AthenaGlider:umbrella_rankedstill"
          }
        ]
      },
      "RankedCupDuosReload_Silver_LeaderboardDef": {
        "scoringRuleSetId": "ScoringRules_RankedCupDuosReload_Silver",
        "WindowLocation": "S38_RankedCupReloadDuos_Event2_ASIA_Silver",
        "isMainWindowLeaderboard": false,
        "useIndividualScores": false,
        "onlyScoreTopN": -1,
        "payouts": [
          {
            "scoreId": "",
            "scoringType": "value",
            "threshold": 50,
            "rewardType": "game",
            "quantity": 1,
            "value": "AthenaGlider:umbrella_rankedstill"
          }
        ]
      },
      "RankedCupDuosReload_Gold_LeaderboardDef": {
        "scoringRuleSetId": "ScoringRules_RankedCupDuosReload_Gold",
        "WindowLocation": "S38_RankedCupReloadDuos_Event2_ASIA_gold",
        "isMainWindowLeaderboard": false,
        "useIndividualScores": false,
        "onlyScoreTopN": -1,
        "payouts": [
          {
            "scoreId": "",
            "scoringType": "value",
            "threshold": 50,
            "rewardType": "game",
            "quantity": 1,
            "value": "AthenaGlider:umbrella_rankedstill"
          }
        ]
      },
      "RankedCupDuosReload_Platinum_LeaderboardDef": {
        "scoringRuleSetId": "ScoringRules_RankedCupDuosReload_Platinum",
        "WindowLocation": "S38_RankedCupReloadDuos_Event2_ASIA_platinum",
        "isMainWindowLeaderboard": false,
        "useIndividualScores": false,
        "onlyScoreTopN": -1,
        "payouts": [
          {
            "scoreId": "",
            "scoringType": "value",
            "threshold": 50,
            "rewardType": "game",
            "quantity": 1,
            "value": "AthenaGlider:umbrella_rankedstill"
          }
        ]
      },
      "RankedCupDuosReload_Diamond_LeaderboardDef": {
        "scoringRuleSetId": "ScoringRules_RankedCupDuosReload_Diamond",
        "WindowLocation": "S38_RankedCupReloadDuos_Event2_ASIA_diamond",
        "isMainWindowLeaderboard": false,
        "useIndividualScores": false,
        "onlyScoreTopN": -1,
        "payouts": [
          {
            "scoreId": "",
            "scoringType": "value",
            "threshold": 50,
            "rewardType": "game",
            "quantity": 1,
            "value": "AthenaGlider:umbrella_rankedstill"
          }
        ]
      },
      "RankedCupDuosReload_Elite_LeaderboardDef": {
        "scoringRuleSetId": "ScoringRules_RankedCupDuosReload_Elite",
        "WindowLocation": "S38_RankedCupReloadDuos_Event2_ASIA_elite",
        "isMainWindowLeaderboard": false,
        "useIndividualScores": false,
        "onlyScoreTopN": -1,
        "payouts": [
          {
            "scoreId": "",
            "scoringType": "value",
            "threshold": 50,
            "rewardType": "game",
            "quantity": 1,
            "value": "AthenaGlider:umbrella_rankedstill"
          }
        ]
      },
      "RankedCupDuosReload_Champion_LeaderboardDef": {
        "scoringRuleSetId": "ScoringRules_RankedCupDuosReload_Champion",
        "WindowLocation": "S38_RankedCupReloadDuos_Event2_ASIA_champion",
        "isMainWindowLeaderboard": false,
        "useIndividualScores": false,
        "onlyScoreTopN": -1,
        "payouts": [
          {
            "scoreId": "",
            "scoringType": "value",
            "threshold": 50,
            "rewardType": "game",
            "quantity": 1,
            "value": "AthenaGlider:umbrella_rankedstill"
          }
        ]
      },
      "RankedCupDuosReload_Unreal_LeaderboardDef": {
        "scoringRuleSetId": "ScoringRules_RankedCupDuosReload_Unreal",
        "WindowLocation": "S38_RankedCupReloadDuos_Event2_ASIA_unreal",
        "isMainWindowLeaderboard": false,
        "useIndividualScores": false,
        "onlyScoreTopN": -1,
        "payouts": [
          {
            "scoreId": "",
            "scoringType": "value",
            "threshold": 50,
            "rewardType": "game",
            "quantity": 1,
            "value": "AthenaGlider:umbrella_rankedstill"
          }
        ]
      }
    }
  }
}